cleantoots/__init__.py
cleantoots/commands/__init__.py
cleantoots/commands/clean.py
cleantoots/commands/config.py
cleantoots/main.py
cleantoots/utils.py
cleantoots-0.7.0.dist-info/entry_points.txt
cleantoots-0.7.0.dist-info/LICENSE
cleantoots-0.7.0.dist-info/WHEEL
cleantoots-0.7.0.dist-info/METADATA
cleantoots-0.7.0.dist-info/RECORD
