Metadata-Version: 2.1
Name: cleantoots
Version: 0.7.0
Summary: Cleanup your toot history.
Home-page: https://git.augendre.info/gaugendre/cleantoots
Keywords: mastodon,toot
Author: Gabriel Augendre
Author-email: gabriel@augendre.info
Requires-Python: >=3.8,<4
Classifier: Development Status :: 3 - Alpha
Classifier: Environment :: Console
Classifier: Intended Audience :: End Users/Desktop
Classifier: License :: OSI Approved :: The Unlicense (Unlicense)
Classifier: Programming Language :: Python :: 3
Classifier: Programming Language :: Python :: 3.10
Classifier: Programming Language :: Python :: 3.8
Classifier: Programming Language :: Python :: 3.9
Classifier: Topic :: Communications :: Chat
Classifier: Topic :: Utilities
Requires-Dist: Mastodon.py (>=1.5.0)
Requires-Dist: click (>=7.0)
Requires-Dist: html2text (>=2019.9.26)
Requires-Dist: pendulum (>=2.0.5)
Project-URL: Repository, https://git.augendre.info/gaugendre/cleantoots
